dorsal/__init__.py
dorsal/py.typed
dorsal/session.py
dorsal/testing.py
dorsal/version.py
dorsal/api/__init__.py
dorsal/api/collection.py
dorsal/api/config.py
dorsal/api/dataset.py
dorsal/api/file.py
dorsal/cli/__init__.py
dorsal/cli/auth_app.py
dorsal/cli/config_app.py
dorsal/cli/search_app.py
dorsal/cli/cache_app/__init__.py
dorsal/cli/cache_app/build_cache_cmd.py
dorsal/cli/cache_app/clear_cache_cmd.py
dorsal/cli/cache_app/export_cmd.py
dorsal/cli/cache_app/optimize_cache_cmd.py
dorsal/cli/cache_app/path_cache_cmd.py
dorsal/cli/cache_app/prune_cache_cmd.py
dorsal/cli/cache_app/show_cache_cmd.py
dorsal/cli/collection_app/__init__.py
dorsal/cli/collection_app/add_files_cmd.py
dorsal/cli/collection_app/delete_cmd.py
dorsal/cli/collection_app/export_cmd.py
dorsal/cli/collection_app/list_cmd.py
dorsal/cli/collection_app/make_private_cmd.py
dorsal/cli/collection_app/make_public_cmd.py
dorsal/cli/collection_app/remove_files_cmd.py
dorsal/cli/collection_app/show_cmd.py
dorsal/cli/collection_app/update_cmd.py
dorsal/cli/dir_app/__init__.py
dorsal/cli/dir_app/duplicates_dir_cmd.py
dorsal/cli/dir_app/info_dir_cmd.py
dorsal/cli/dir_app/push_dir_cmd.py
dorsal/cli/dir_app/scan_dir_cmd.py
dorsal/cli/file_app/__init__.py
dorsal/cli/file_app/hash_cmd.py
dorsal/cli/file_app/identify_cmd.py
dorsal/cli/file_app/push_cmd.py
dorsal/cli/file_app/report_cmd.py
dorsal/cli/file_app/scan_cmd.py
dorsal/cli/record_app/__init__.py
dorsal/cli/record_app/delete_cmd.py
dorsal/cli/record_app/get_cmd.py
dorsal/cli/record_app/search_cmd.py
dorsal/cli/record_app/tag_app.py
dorsal/cli/themes/palettes.py
dorsal/cli/views/collection.py
dorsal/cli/views/file.py
dorsal/cli/views/mediainfo.py
dorsal/client/__init__.py
dorsal/client/dorsal_client.py
dorsal/client/validators.py
dorsal/common/__init__.py
dorsal/common/auth.py
dorsal/common/cli.py
dorsal/common/config.py
dorsal/common/constants.py
dorsal/common/environment.py
dorsal/common/exceptions.py
dorsal/common/literals.py
dorsal/common/model.py
dorsalhub-0.4.0.dist-info/METADATA
dorsalhub-0.4.0.dist-info/WHEEL
dorsalhub-0.4.0.dist-info/entry_points.txt
dorsalhub-0.4.0.dist-info/licenses/LICENSE
dorsalhub-0.4.0.dist-info/licenses/NOTICE
dorsalhub-0.4.0.dist-info/RECORD
