Metadata-Version: 2.4
Name: dorsalhub
Version: 0.4.0
Summary: Dorsal is a local-first metadata generation and management toolkit.
Project-URL: Homepage, https://dorsalhub.com
Project-URL: Repository, https://github.com/dorsalhub/dorsal
Project-URL: Documentation, https://docs.dorsalhub.com
Author-email: Rio Achuzia <rio@dorsalhub.com>
License: Apache-2.0
License-File: LICENSE
License-File: NOTICE
Classifier: Development Status :: 4 - Beta
Classifier: License :: OSI Approved :: Apache Software License
Classifier: Operating System :: OS Independent
Classifier: Programming Language :: Python :: 3
Classifier: Programming Language :: Python :: 3.11
Classifier: Programming Language :: Python :: 3.12
Classifier: Programming Language :: Python :: 3.13
Classifier: Programming Language :: Python :: 3.14
Requires-Python: >=3.11
Requires-Dist: blake3>=1.0.8
Requires-Dist: jinja2>=3.1.6
Requires-Dist: jsonschema-rs>=0.38.1
Requires-Dist: langcodes[data]==3.5.0
Requires-Dist: pydantic>=2.12.1
Requires-Dist: pymediainfo>=6.1.0
Requires-Dist: pypdfium2>=5.2.0
Requires-Dist: python-dateutil>=2.9.0.post0
Requires-Dist: python-magic-bin>=0.4.14; sys_platform == 'win32'
Requires-Dist: python-magic>=0.4.27; sys_platform == 'linux' or sys_platform == 'darwin'
Requires-Dist: requests<3.0,>=2.32.3
Requires-Dist: rich>=14.0.0
Requires-Dist: textual>=6.2.1
Requires-Dist: tomlkit>=0.12.0
Requires-Dist: tqdm>=4.67.1
Requires-Dist: typer>=0.16.0
Provides-Extra: all
Requires-Dist: pandas>=2.0.0; extra == 'all'
Requires-Dist: py-tlsh>=4.7.2; extra == 'all'
Provides-Extra: pandas
Requires-Dist: pandas>=2.0.0; extra == 'pandas'
Provides-Extra: tlsh
Requires-Dist: py-tlsh>=4.7.2; extra == 'tlsh'
